README.md
setup.py
precacher/__main__.py
precacher.egg-info/PKG-INFO
precacher.egg-info/SOURCES.txt
precacher.egg-info/dependency_links.txt
precacher.egg-info/entry_points.txt
precacher.egg-info/requires.txt
precacher.egg-info/top_level.txt