Metadata-Version: 1.2
Name: precacher
Version: 0.1.0
Summary: Replays DNS queries from Pi-hole or dnscrypt-proxy.
Home-page: https://github.com/dcoker/precacher/
Author: Doug Coker
Author-email: dcoker@gmail.com
License: https://www.apache.org/licenses/LICENSE-2.0
Platform: UNKNOWN
Requires-Python: >=3.6.0
